vartracker/__init__.py
vartracker/_version.py
vartracker/amino_acids.py
vartracker/analysis.py
vartracker/constants.py
vartracker/core.py
vartracker/main.py
vartracker/vcf_processing.py
vartracker/data/NC_045512.fasta
vartracker/data/NC_045512.fasta.fai
vartracker/data/NC_045512.gff3
vartracker/data/__init__.py
vartracker/data/parse_pokay.py
vartracker/test_data/coverage/test_psg_0.coverage.txt
vartracker/test_data/coverage/test_psg_1.coverage.txt
vartracker/test_data/coverage/test_psg_12.coverage.txt
vartracker/test_data/coverage/test_psg_15.coverage.txt
vartracker/test_data/coverage/test_psg_2.coverage.txt
vartracker/test_data/coverage/test_psg_3.coverage.txt
vartracker/test_data/coverage/test_psg_4.coverage.txt
vartracker/test_data/coverage/test_psg_5.coverage.txt
vartracker/test_data/coverage/test_psg_6.coverage.txt
vartracker/test_data/coverage/test_psg_9.coverage.txt
vartracker/test_data/inputs/test_input.csv
vartracker/test_data/mock_pokay/mock_pokay.csv
vartracker/test_data/precomputed/test_results.csv
vartracker/test_data/vcfs/test_psg_0.lofreq.vcf.gz
vartracker/test_data/vcfs/test_psg_0.lofreq.vcf.gz.csi
vartracker/test_data/vcfs/test_psg_1.lofreq.vcf.gz
vartracker/test_data/vcfs/test_psg_1.lofreq.vcf.gz.csi
vartracker/test_data/vcfs/test_psg_12.lofreq.vcf.gz
vartracker/test_data/vcfs/test_psg_12.lofreq.vcf.gz.csi
vartracker/test_data/vcfs/test_psg_15.lofreq.vcf.gz
vartracker/test_data/vcfs/test_psg_15.lofreq.vcf.gz.csi
vartracker/test_data/vcfs/test_psg_2.lofreq.vcf.gz
vartracker/test_data/vcfs/test_psg_2.lofreq.vcf.gz.csi
vartracker/test_data/vcfs/test_psg_3.lofreq.vcf.gz
vartracker/test_data/vcfs/test_psg_3.lofreq.vcf.gz.csi
vartracker/test_data/vcfs/test_psg_4.lofreq.vcf.gz
vartracker/test_data/vcfs/test_psg_4.lofreq.vcf.gz.csi
vartracker/test_data/vcfs/test_psg_5.lofreq.vcf.gz
vartracker/test_data/vcfs/test_psg_5.lofreq.vcf.gz.csi
vartracker/test_data/vcfs/test_psg_6.lofreq.vcf.gz
vartracker/test_data/vcfs/test_psg_6.lofreq.vcf.gz.csi
vartracker-1.0.2.dist-info/METADATA
vartracker-1.0.2.dist-info/WHEEL
vartracker-1.0.2.dist-info/entry_points.txt
vartracker-1.0.2.dist-info/licenses/LICENSE
vartracker-1.0.2.dist-info/RECORD
