Metadata-Version: 2.4
Name: vartracker
Version: 1.0.2
Summary: Track the persistence (or loss) of mutations during long-term passaging
Project-URL: Homepage, https://github.com/charlesfoster/vartracker
Project-URL: Bug Reports, https://github.com/charlesfoster/vartracker/issues
Project-URL: Source, https://github.com/charlesfoster/vartracker
Project-URL: Documentation, https://github.com/charlesfoster/vartracker/blob/main/README.md
Author: Dr Charles Foster
Maintainer-email: Dr Charles Foster <charles.foster@unsw.edu.au>
License-Expression: MIT
License-File: LICENSE
Keywords: SARS-CoV-2,VCF,bioinformatics,genomics,longitudinal-analysis,mutation-tracking,passaging,variant-analysis
Classifier: Development Status :: 5 - Production/Stable
Classifier: Intended Audience :: Science/Research
Classifier: Operating System :: OS Independent
Classifier: Programming Language :: Python :: 3
Classifier: Programming Language :: Python :: 3.9
Classifier: Programming Language :: Python :: 3.10
Classifier: Programming Language :: Python :: 3.11
Classifier: Programming Language :: Python :: 3.12
Classifier: Programming Language :: Python :: 3.13
Classifier: Topic :: Scientific/Engineering :: Bio-Informatics
Classifier: Topic :: Scientific/Engineering :: Medical Science Apps.
Requires-Python: >=3.10
Requires-Dist: argparse-formatter>=1.4
Requires-Dist: cyvcf2>=0.30.0
Requires-Dist: matplotlib>=3.5.0
Requires-Dist: numpy>=1.20.0
Requires-Dist: pandas>=1.3.0
Requires-Dist: seaborn>=0.11.0
Requires-Dist: urlextract>=1.9.0
Provides-Extra: dev
Requires-Dist: black; extra == 'dev'
Requires-Dist: flake8; extra == 'dev'
Requires-Dist: mypy; extra == 'dev'
Requires-Dist: pre-commit>=3.6; extra == 'dev'
Requires-Dist: pytest-cov; extra == 'dev'
Requires-Dist: pytest>=6.0; extra == 'dev'
Provides-Extra: test
Requires-Dist: pytest; extra == 'test'
Requires-Dist: pytest-cov; extra == 'test'
